telenotipy/__init__.py
telenotipy/client.py
telenotipy-0.0.2.dist-info/METADATA
telenotipy-0.0.2.dist-info/WHEEL
telenotipy-0.0.2.dist-info/top_level.txt
telenotipy-0.0.2.dist-info/RECORD
