Metadata-Version: 2.1
Name: telenotipy
Version: 0.0.2
Summary: Python client to interact with TeleNoti API
Home-page: https://gitlab.forge.hefr.ch/vincent.jaquet/humantech-telegram-notification
Author: Jaquet Vincent
Author-email: vincent.jaquet@edu.hefr.ch
License: UNKNOWN
Platform: UNKNOWN
Classifier: License :: OSI Approved :: GNU General Public License v3 (GPLv3)
Classifier: Intended Audience :: Developers
Classifier: Programming Language :: Python
Classifier: Programming Language :: Python :: 3
Classifier: Programming Language :: Python :: 3.5
Classifier: Programming Language :: Python :: 3.6
Classifier: Programming Language :: Python :: 3.7
Classifier: Programming Language :: Python :: 3.8
Classifier: Programming Language :: Python :: 3 :: Only
Classifier: Operating System :: OS Independent
Requires-Python: >=3.5
Requires-Dist: requests
